mcp_server/__init__.py
mcp_server/application.py
mcp_server/server.py
mcp_server/config/__init__.py
mcp_server/config/config.py
mcp_server/consts/__init__.py
mcp_server/consts/consts.py
mcp_server/core/__init__.py
mcp_server/core/media_processing/__init__.py
mcp_server/core/media_processing/tools.py
mcp_server/core/media_processing/utils.py
mcp_server/core/storage/__init__.py
mcp_server/core/storage/resource.py
mcp_server/core/storage/storage.py
mcp_server/core/storage/tools.py
mcp_server/core/version/__init__.py
mcp_server/core/version/tools.py
mcp_server/core/version/version.py
mcp_server/resource/__init__.py
mcp_server/resource/resource.py
mcp_server/tools/__init__.py
mcp_server/tools/tools.py
sufy_mcp_server-1.0.0.dist-info/METADATA
sufy_mcp_server-1.0.0.dist-info/WHEEL
sufy_mcp_server-1.0.0.dist-info/entry_points.txt
sufy_mcp_server-1.0.0.dist-info/licenses/LICENSE.txt
sufy_mcp_server-1.0.0.dist-info/RECORD
