Metadata-Version: 2.4
Name: sufy-mcp-server
Version: 1.0.0
Summary: A MCP server project of Sufy.
License-File: LICENSE.txt
Requires-Python: >=3.12
Requires-Dist: aioboto3>=13.2.0
Requires-Dist: fastjsonschema>=2.21.1
Requires-Dist: httpx>=0.28.1
Requires-Dist: mcp[cli]>=1.0.0
Requires-Dist: openai>=1.66.3
Requires-Dist: pip>=25.0.1
Requires-Dist: python-dotenv>=1.0.1
